quantuloop/pbw/__init__.py
quantuloop/pbw/libpbw.so
quantuloop/pbw/lib/libpbw10d.so
quantuloop/pbw/lib/libpbw10f.so
quantuloop/pbw/lib/libpbw11d.so
quantuloop/pbw/lib/libpbw11f.so
quantuloop/pbw/lib/libpbw12d.so
quantuloop/pbw/lib/libpbw12f.so
quantuloop/pbw/lib/libpbw1d.so
quantuloop/pbw/lib/libpbw1f.so
quantuloop/pbw/lib/libpbw2d.so
quantuloop/pbw/lib/libpbw2f.so
quantuloop/pbw/lib/libpbw3d.so
quantuloop/pbw/lib/libpbw3f.so
quantuloop/pbw/lib/libpbw4d.so
quantuloop/pbw/lib/libpbw4f.so
quantuloop/pbw/lib/libpbw5d.so
quantuloop/pbw/lib/libpbw5f.so
quantuloop/pbw/lib/libpbw6d.so
quantuloop/pbw/lib/libpbw6f.so
quantuloop/pbw/lib/libpbw7d.so
quantuloop/pbw/lib/libpbw7f.so
quantuloop/pbw/lib/libpbw8d.so
quantuloop/pbw/lib/libpbw8f.so
quantuloop/pbw/lib/libpbw9d.so
quantuloop/pbw/lib/libpbw9f.so
pbw-0.1.1.dist-info/LICENSE
pbw-0.1.1.dist-info/METADATA
pbw-0.1.1.dist-info/WHEEL
pbw-0.1.1.dist-info/top_level.txt
pbw-0.1.1.dist-info/RECORD
pbw.libs/libgomp-a34b3233.so.1.0.0
