Metadata-Version: 2.1
Name: pbw
Version: 0.1.1
Summary: PBW simulator for the Ket Quantum Programming Language.
Author: Quantuloop
License: Quantuloop Quantum Simulator Suite EULA
Requires-Python: >=3.7
License-File: LICENSE
Requires-Dist: PyJWT (>=2.4.0)
Requires-Dist: cryptography (>=37.0)
Requires-Dist: ket-lang (<0.6.0,>=0.5.0)
